Part 1/group22Part1.v
module testbed;
	reg [7:0]OPERAND1;
	reg signed[7:0]OPERAND2;
	reg [2:0]ALUOP;
	wire signed [7:0] ALURESULT;
	
	//instantiate alu module
	alu a1(.DATA1(OPERAND1),.DATA2(OPERAND2),.RESULT(ALURESULT),.SELECT(ALUOP));
	
	initial begin
	//assign values to inputs to get the outputs
	OPERAND1 = 8'd100;
	OPERAND2 = 8'd20;
	ALUOP = 3'd0;
	#5
	
	OPERAND1 = 8'd95;
	OPERAND2 = 8'd10;
	ALUOP = 3'd1;
	#5
	
	OPERAND1 = 8'd110;
	OPERAND2 = 8'd128;
	ALUOP = 3'd1;
	#5
	
	OPERAND1 = 8'd4;
	OPERAND2 = 8'd4;
	ALUOP = 3'd2;
	#5;
	
	OPERAND1 = 8'd5;
	OPERAND2 = 8'd6;
	ALUOP = 3'd3;
	#5
	$finish;
	end
	
	initial begin
		//display variable values in every change of variables
		$monitor("Time = %g\tALUOP=%d\t\tOPERRAND1=%d\t\tOPERAND2=%d\t\tALURESULT= %d",$time,ALUOP,OPERAND1,OPERAND2,ALURESULT);
		
		//generate files needed to plot the waveform using GTKWave
		$dumpfile("data1.vcd");
        $dumpvars(0,testbed);	
	end
	
endmodule	

module alu(DATA1,DATA2,RESULT,SELECT);
	//Port declaration
	input [7:0] DATA1;					//8 bit unsigned input 
	input signed [7:0] DATA2;			//8 bit signed input
	input [2:0] SELECT;					//3 bit unsigned input
	output reg signed[7:0] RESULT;		//8 bit signed input register
	
	wire [7:0] FORWARD_RESULT,AND_RESULT,OR_RESULT,ADD_RESULT; //8 bit wires to collect design outputs

	//instantiate FORWARD module
	FORWARD myforward(DATA2,FORWARD_RESULT);
	//instantiate AND module	
	AND myand(DATA1,DATA2,AND_RESULT);
	//instantiate OR module
	OR myor(DATA1,DATA2,OR_RESULT);
	//instantiate ADD module
	ADD myadd(DATA1,DATA2,ADD_RESULT);

	//Get executed whenever the values SELECT,FORWARD_RESULT,AND_RESULT,ADD_RESULT and OR_RESULT changes
	always @(SELECT or FORWARD_RESULT or AND_RESULT or ADD_RESULT or OR_RESULT)
	//Select the result based on the value of the selecct signal
	begin
		case(SELECT)
			3'b000 : RESULT = FORWARD_RESULT; 
			3'b001 : RESULT = ADD_RESULT;
			3'b010 : RESULT = AND_RESULT;
			3'b011 : RESULT = OR_RESULT;
			default:RESULT = 8'b0;
		endcase
	end
endmodule	

//module for FORWARD function
module FORWARD(IN,OUT);
	input [7:0] IN;		//8 bit input
	output [7:0] OUT;	//8 bit output
	
	assign #1 OUT = IN; //assign input to output with 1 unit delay
endmodule	//FORWARD

//module for AND function
module AND(IN1,IN2,OUT);
	input [7:0] IN1,IN2; //8 bit inputs
	output [7:0] OUT;	 //8 bit inputs
	
	assign #1 OUT = IN1 & IN2; //bitwise and on inputs with 1 unit delay
endmodule	//AND

//module for OR function
module OR(IN1,IN2,OUT);
	input [7:0] IN1,IN2; //8 bit inputs
	output [7:0] OUT;    //8 bit output
	
	assign #1 OUT = IN1 | IN2;	//bitwise or on inputs with 1 unit delay
endmodule	//OR

//module for ADD function
module ADD(IN1,IN2,OUT);
	input [7:0] IN1;			//8 bit unsigned input 
	input signed [7:0] IN2;		//8 bit signed input 
	output signed [7:0] OUT;	//8 bit signed output 
	
	assign #2 OUT=IN1+IN2;	//addition of inputs with 2 unit delay
endmodule	//ADD

Part 1/data1.vcd
$date
	Tue Jan 11 22:36:19 2022
$end
$version
	Icarus Verilog
$end
$timescale
	1s
$end
$scope module testbed $end
$var wire 8 ! ALURESULT [7:0] $end
$var reg 3 " ALUOP [2:0] $end
$var reg 8 # OPERAND1 [7:0] $end
$var reg 8 $ OPERAND2 [7:0] $end
$scope module a1 $end
$var wire 8 % DATA1 [7:0] $end
$var wire 8 & DATA2 [7:0] $end
$var wire 3 ' SELECT [2:0] $end
$var wire 8 ( OR_RESULT [7:0] $end
$var wire 8 ) FORWARD_RESULT [7:0] $end
$var wire 8 * AND_RESULT [7:0] $end
$var wire 8 + ADD_RESULT [7:0] $end
$var reg 8 , RESULT [7:0] $end
$scope module myadd $end
$var wire 8 - IN1 [7:0] $end
$var wire 8 . IN2 [7:0] $end
$var wire 8 / OUT [7:0] $end
$upscope $end
$scope module myand $end
$var wire 8 0 IN1 [7:0] $end
$var wire 8 1 IN2 [7:0] $end
$var wire 8 2 OUT [7:0] $end
$upscope $end
$scope module myforward $end
$var wire 8 3 IN [7:0] $end
$var wire 8 4 OUT [7:0] $end
$upscope $end
$scope module myor $end
$var wire 8 5 IN1 [7:0] $end
$var wire 8 6 IN2 [7:0] $end
$var wire 8 7 OUT [7:0] $end
$upscope $end
$upscope $end
$upscope $end
$enddefinitions $end
#0
$dumpvars
bx 7
b10100 6
b1100100 5
bx 4
b10100 3
bx 2
b10100 1
b1100100 0
bx /
b10100 .
b1100100 -
bx ,
bx +
bx *
bx )
bx (
b0 '
b10100 &
b1100100 %
b10100 $
b1100100 #
b0 "
bx !
$end
#1
b10100 !
b10100 ,
b1110100 (
b1110100 7
b100 *
b100 2
b10100 )
b10100 4
#2
b1111000 +
b1111000 /
#5
b1111000 !
b1111000 ,
b1 "
b1 '
b1010 $
b1010 &
b1010 .
b1010 1
b1010 3
b1010 6
b1011111 #
b1011111 %
b1011111 -
b1011111 0
b1011111 5
#6
b1010 *
b1010 2
b1011111 (
b1011111 7
b1010 )
b1010 4
#7
b1101001 !
b1101001 ,
b1101001 +
b1101001 /
#10
b10000000 $
b10000000 &
b10000000 .
b10000000 1
b10000000 3
b10000000 6
b1101110 #
b1101110 %
b1101110 -
b1101110 0
b1101110 5
#11
b0 *
b0 2
b11101110 (
b11101110 7
b10000000 )
b10000000 4
#12
b11101110 !
b11101110 ,
b11101110 +
b11101110 /
#15
b0 !
b0 ,
b10 "
b10 '
b100 $
b100 &
b100 .
b100 1
b100 3
b100 6
b100 #
b100 %
b100 -
b100 0
b100 5
#16
b100 !
b100 ,
b100 *
b100 2
b100 (
b100 7
b100 )
b100 4
#17
b1000 +
b1000 /
#20
b11 "
b11 '
b110 $
b110 &
b110 .
b110 1
b110 3
b110 6
b101 #
b101 %
b101 -
b101 0
b101 5
#21
b111 !
b111 ,
b111 (
b111 7
b110 )
b110 4
#22
b1011 +
b1011 /
